NAVIAI4/__init__.py
escaper_temp/__init__.py
escaper_utilities/__init__.py
escaper_utils/__init__.py
escaper_utils/augmentation.cp310-win_amd64.pyd
escaper_utils/augmentation.cp36-win_amd64.pyd
escaper_utils/augmentation.cp37-win_amd64.pyd
escaper_utils/augmentation.cp38-win_amd64.pyd
escaper_utils/augmentation.cp39-win_amd64.pyd
escaper_utils/augmentation.cpython-310-x86_64-linux-gnu.so
escaper_utils/augmentation.cpython-36m-x86_64-linux-gnu.so
escaper_utils/augmentation.cpython-37m-x86_64-linux-gnu.so
escaper_utils/augmentation.cpython-38-x86_64-linux-gnu.so
escaper_utils/augmentation.cpython-39-x86_64-linux-gnu.so
escaper_utils/classification.cp310-win_amd64.pyd
escaper_utils/classification.cp36-win_amd64.pyd
escaper_utils/classification.cp37-win_amd64.pyd
escaper_utils/classification.cp38-win_amd64.pyd
escaper_utils/classification.cp39-win_amd64.pyd
escaper_utils/classification.cpython-310-x86_64-linux-gnu.so
escaper_utils/classification.cpython-36m-x86_64-linux-gnu.so
escaper_utils/classification.cpython-37m-x86_64-linux-gnu.so
escaper_utils/classification.cpython-38-x86_64-linux-gnu.so
escaper_utils/classification.cpython-39-x86_64-linux-gnu.so
escaper_utils/eda.cp310-win_amd64.pyd
escaper_utils/eda.cp36-win_amd64.pyd
escaper_utils/eda.cp37-win_amd64.pyd
escaper_utils/eda.cp38-win_amd64.pyd
escaper_utils/eda.cp39-win_amd64.pyd
escaper_utils/object_detection.cp310-win_amd64.pyd
escaper_utils/object_detection.cp36-win_amd64.pyd
escaper_utils/object_detection.cp37-win_amd64.pyd
escaper_utils/object_detection.cp38-win_amd64.pyd
escaper_utils/object_detection.cp39-win_amd64.pyd
escaper_utils/object_detection.cpython-310-x86_64-linux-gnu.so
escaper_utils/object_detection.cpython-36m-x86_64-linux-gnu.so
escaper_utils/object_detection.cpython-37m-x86_64-linux-gnu.so
escaper_utils/object_detection.cpython-38-x86_64-linux-gnu.so
escaper_utils/object_detection.cpython-39-x86_64-linux-gnu.so
escaper_utils/recognition.cp310-win_amd64.pyd
escaper_utils-2.9.22.dist-info/METADATA
escaper_utils-2.9.22.dist-info/WHEEL
escaper_utils-2.9.22.dist-info/top_level.txt
escaper_utils-2.9.22.dist-info/RECORD
