Metadata-Version: 2.1
Name: escaper-utils
Version: 2.9.22
Summary: escaper_utils
Home-page: 
Download-URL: 
Author: sike6054
Author-email: sike6054@gmail.com
Classifier: Programming Language :: Python :: 3.6
Classifier: Programming Language :: Python :: 3.7
Classifier: Programming Language :: Python :: 3.8
Classifier: Programming Language :: Python :: 3.9
Classifier: Programming Language :: Python :: 3.10
Classifier: Operating System :: Microsoft :: Windows
Classifier: Operating System :: Unix
Requires-Python: >=3.6, <3.11
Requires-Dist: albumentations (==1.0.3)
Requires-Dist: dill (==0.3.6)
Requires-Dist: tqdm
Requires-Dist: pyyaml
Requires-Dist: numpy (>=1.21)
Requires-Dist: timm (==0.6.12)
Requires-Dist: pillow (>=9.3.0)
Requires-Dist: pandas
Requires-Dist: scikit-learn
Requires-Dist: torchmetrics (==0.11.1)
Requires-Dist: seaborn
Requires-Dist: matplotlib
Requires-Dist: natsort
